distnav/__init__.py
distnav/distnav.py
distnav/distnav_utils.py
distnav-0.0.1.dist-info/LICENSE
distnav-0.0.1.dist-info/METADATA
distnav-0.0.1.dist-info/WHEEL
distnav-0.0.1.dist-info/top_level.txt
distnav-0.0.1.dist-info/RECORD
