Metadata-Version: 2.1
Name: distnav
Version: 0.0.1
Summary: DistNav crowd navigation toolbox
Home-page: https://github.com/MurpheyLab/DistNav
Author: Muchen Sun
License: UNKNOWN
Platform: UNKNOWN
Requires-Python: >=3.6
Requires-Dist: numpy
Requires-Dist: numba
